{
  "schema_version": "ar_forward_output_v1",
  "request_kind": "fit_layer",
  "request": {
    "schema_version": "ar_forward_input_v1",
    "request_kind": "fit_layer",
    "request_label": "fit-layer",
    "pairing_control_mode": "delta_from_baseline_meV",
    "pairing_controls": {
      "delta_zz_s": 0.1,
      "delta_perp_x": -0.1
    },
    "allow_weak_delta_zx_s": false,
    "transport": {
      "direction_mode": "inplane_110",
      "interface_angle": 0.7853981633974483,
      "barrier_z": 0.5,
      "gamma": 1.0,
      "temperature_kelvin": 3.0,
      "nk": 21
    },
    "bias_grid": {
      "bias_min_mev": -30.0,
      "bias_max_mev": 30.0,
      "num_bias": 81
    }
  },
  "metadata": {
    "forward_interface_version": "ar_forward_v1",
    "output_schema_version": "ar_forward_output_v1",
    "pairing_convention_id": "round2_physical_channels_task_h_fit_layer_v1",
    "pairing_source": "task_h_fit_layer_controls",
    "normal_state_policy": "repository_fixed_base_normal_state",
    "normal_state_family": "base",
    "truth_layer": "round2_physical_pairing_channels",
    "fit_layer_policy": {
      "free_channels": [
        "delta_zz_s",
        "delta_xx_s",
        "delta_zx_d",
        "delta_perp_z",
        "delta_perp_x"
      ],
      "strongly_regularized_channels": [
        "delta_zz_d",
        "delta_xx_d"
      ],
      "weak_optional_channels": [
        "delta_zx_s"
      ],
      "default_complex_phase_policy": "fixed_real_controls_in_projection_gauge"
    },
    "projection_config": {
      "block_weights": {
        "delta_x": 1.0,
        "delta_y": 1.0,
        "delta_z": 1.15
      },
      "source_entry_weight_mode": "uniform",
      "freeze_optional_weak_channel_by_default": true,
      "optional_weak_channel_name": "delta_zx_s",
      "optional_channel_activation_min_relative_magnitude": 0.08,
      "optional_channel_activation_min_residual_reduction": 0.01,
      "ar_interface_angles": [
        0.0,
        0.7853981633974483
      ],
      "ar_reference_nk": 61,
      "ar_supported_entry_weight_floor": 0.75,
      "ar_unsupported_entry_weight": 0.15,
      "channel_regularization": {
        "delta_zz_s": 0.0001,
        "delta_zz_d": 0.0002,
        "delta_xx_s": 0.0001,
        "delta_xx_d": 0.0001,
        "delta_zx_s": 0.005,
        "delta_zx_d": 0.00075,
        "delta_perp_z": 0.0001,
        "delta_perp_x": 0.00075
      },
      "core_channels": [
        "delta_zz_s",
        "delta_zz_d",
        "delta_xx_s",
        "delta_xx_d",
        "delta_zx_d",
        "delta_perp_z",
        "delta_perp_x"
      ],
      "optional_channels": [
        "delta_zx_s"
      ],
      "gauge_anchor_priority": [
        "delta_zz_s",
        "delta_zz_d",
        "delta_xx_s",
        "delta_xx_d",
        "delta_zx_d",
        "delta_perp_z",
        "delta_perp_x",
        "delta_zx_s"
      ],
      "gauge_min_anchor_abs": 1e-10
    },
    "formal_baseline_record": "outputs/source/round2_baseline_selection.json",
    "formal_baseline_role": "authoritative_formal_round2_baseline",
    "formal_baseline_selection_rule": "temperature sweep RMFT pairing data, charge-balanced p\u22480 branch, temperature_eV <= 1.0e-3, first 8 samples sorted by temperature",
    "weak_channel_policy": {
      "channel": "delta_zx_s",
      "default_task_c_freeze_applied": true,
      "default_value": {
        "re": 0.0,
        "im": 0.0
      }
    },
    "git_commit": "4e4c935d1f123c03ee2250f8624d5df3c2c7ebe3",
    "git_dirty": false,
    "fit_layer_request_label": "fit-layer",
    "pairing_control_mode": "delta_from_baseline_meV",
    "allow_weak_delta_zx_s": false
  },
  "pairing_channels": {
    "delta_zz_s": {
      "re": 43.57120957876886,
      "im": -5.990118039475454e-16
    },
    "delta_zz_d": {
      "re": -6.466862302353315e-08,
      "im": 1.2953226292173953e-07
    },
    "delta_xx_s": {
      "re": -1.7820360737854517,
      "im": 1.2994633925908852e-12
    },
    "delta_xx_d": {
      "re": -1.3049740214993564e-07,
      "im": 2.5302036891064664e-07
    },
    "delta_zx_s": {
      "re": 0.0,
      "im": 0.0
    },
    "delta_zx_d": {
      "re": -3.5075801360800885,
      "im": 4.107408423357123e-14
    },
    "delta_perp_z": {
      "re": -63.5131723333877,
      "im": 4.192049956675495e-13
    },
    "delta_perp_x": {
      "re": -10.277615214844031,
      "im": -1.733867852682211e-14
    }
  },
  "bias_mev": [
    -30.0,
    -29.25,
    -28.5,
    -27.75,
    -27.0,
    -26.25,
    -25.5,
    -24.75,
    -24.0,
    -23.25,
    -22.5,
    -21.75,
    -21.0,
    -20.25,
    -19.5,
    -18.75,
    -18.0,
    -17.25,
    -16.5,
    -15.75,
    -15.0,
    -14.25,
    -13.5,
    -12.75,
    -12.0,
    -11.25,
    -10.5,
    -9.75,
    -9.0,
    -8.25,
    -7.5,
    -6.75,
    -6.0,
    -5.25,
    -4.5,
    -3.75,
    -3.0,
    -2.25,
    -1.5,
    -0.75,
    0.0,
    0.75,
    1.5,
    2.25,
    3.0,
    3.75,
    4.5,
    5.25,
    6.0,
    6.75,
    7.5,
    8.25,
    9.0,
    9.75,
    10.5,
    11.25,
    12.0,
    12.75,
    13.5,
    14.25,
    15.0,
    15.75,
    16.5,
    17.25,
    18.0,
    18.75,
    19.5,
    20.25,
    21.0,
    21.75,
    22.5,
    23.25,
    24.0,
    24.75,
    25.5,
    26.25,
    27.0,
    27.75,
    28.5,
    29.25,
    30.0
  ],
  "conductance": [
    1.0164465032698036,
    1.0088176461952405,
    1.001422112951567,
    0.9950982119289811,
    0.9903941795913991,
    0.9878213460630096,
    0.9878336736637136,
    0.9899366517827899,
    0.9909371298916423,
    0.9881490608568574,
    0.98322245737656,
    0.9782917638008751,
    0.9745700869577494,
    0.9727761206855478,
    0.9735373048900018,
    0.9776342467197421,
    0.9861918153710892,
    1.0005999549610287,
    1.0207510574184746,
    1.04057133958412,
    1.0518416396214942,
    1.0538267262945744,
    1.0508055209006437,
    1.044931005364602,
    1.0356306206076342,
    1.0203621472577438,
    1.0010849124951164,
    0.9802821529405366,
    0.9579265711323691,
    0.9356458250300911,
    0.9151469165046426,
    0.8970812644827505,
    0.8815052786795834,
    0.8682766236735565,
    0.8572109959205871,
    0.8481346673480488,
    0.8409003249462634,
    0.8353903414388637,
    0.831515963132192,
    0.8292155008933253,
    0.8284526701316526,
    0.8292155008933251,
    0.8315159631321922,
    0.8353903414388637,
    0.8409003249462634,
    0.8481346673480488,
    0.8572109959205874,
    0.8682766236735565,
    0.8815052786795834,
    0.8970812644827505,
    0.9151469165046427,
    0.935645825030091,
    0.9579265711323692,
    0.9802821529405368,
    1.0010849124951164,
    1.0203621472577438,
    1.0356306206076342,
    1.044931005364602,
    1.0508055209006437,
    1.0538267262945744,
    1.0518416396214942,
    1.04057133958412,
    1.0207510574184746,
    1.0005999549610287,
    0.9861918153710892,
    0.9776342467197421,
    0.9735373048900018,
    0.9727761206855478,
    0.9745700869577494,
    0.9782917638008751,
    0.98322245737656,
    0.9881490608568574,
    0.9909371298916423,
    0.9899366517827899,
    0.9878336736637136,
    0.9878213460630096,
    0.9903941795913991,
    0.9950982119289811,
    1.001422112951567,
    1.0088176461952405,
    1.0164465032698036
  ],
  "conductance_unbroadened": [
    0.9868021106067233,
    0.9791336918182095,
    0.9718200302454875,
    0.9655921787399161,
    0.9609390838763205,
    0.9583486977576857,
    0.958395517800916,
    0.9610584880764433,
    0.9625900936033887,
    0.9594954193577153,
    0.9543241060945783,
    0.9493415085961626,
    0.9456128091354008,
    0.9437677944987699,
    0.944375979591026,
    0.9481600311929028,
    0.9561995425866151,
    0.970087506652667,
    0.9907702028432605,
    1.0116579752029398,
    1.0226545458964698,
    1.0236785355553681,
    1.0203841012208466,
    1.0147741180330951,
    1.0063584875224731,
    0.9910905116895605,
    0.9718765546756746,
    0.9518082208559564,
    0.9297771861041029,
    0.9078343296316896,
    0.887838485797164,
    0.8703011674969171,
    0.8552098551851853,
    0.842402369035815,
    0.8316919408402035,
    0.8229076214420267,
    0.8159060043807541,
    0.8105731097892801,
    0.8068231221098021,
    0.804596457320174,
    0.8038580868037569,
    0.804596457320174,
    0.8068231221098021,
    0.8105731097892801,
    0.8159060043807541,
    0.8229076214420267,
    0.8316919408402035,
    0.842402369035815,
    0.8552098551851853,
    0.8703011674969171,
    0.887838485797164,
    0.9078343296316896,
    0.9297771861041029,
    0.9518082208559564,
    0.9718765546756746,
    0.9910905116895605,
    1.0063584875224731,
    1.0147741180330951,
    1.0203841012208466,
    1.0236785355553681,
    1.0226545458964698,
    1.0116579752029398,
    0.9907702028432605,
    0.970087506652667,
    0.9561995425866151,
    0.9481600311929028,
    0.944375979591026,
    0.9437677944987699,
    0.9456128091354008,
    0.9493415085961626,
    0.9543241060945783,
    0.9594954193577153,
    0.9625900936033887,
    0.9610584880764433,
    0.958395517800916,
    0.9583486977576857,
    0.9609390838763205,
    0.9655921787399161,
    0.9718200302454875,
    0.9791336918182095,
    0.9868021106067233
  ],
  "transport_summary": {
    "direction_mode": "inplane_110",
    "direction_support_tier": "A",
    "direction_crystal_label": "110",
    "direction_dimensionality": "2D in-plane",
    "direction_is_named_mode": true,
    "interface_angle": 0.7853981633974483,
    "barrier_z": 0.5,
    "gamma": 1.0,
    "temperature_kelvin": 3.0,
    "nk": 21,
    "num_input_channels": 73,
    "num_channels": 73,
    "num_filtered_channels": 0,
    "num_same_band_channels": 73,
    "num_contours": 7,
    "mean_normal_transparency": 0.8,
    "mean_mismatch_penalty": 1.0,
    "approximation": "2D specular-reflection, band-projected, multichannel phase-sensitive BTK/generalized-KT style solver; still not a full exact coupled multiband interface-scattering theory."
  }
}